opam/__init__.py
opam/opamextract.py
opam-1.0.6.dist-info/LICENSE
opam-1.0.6.dist-info/METADATA
opam-1.0.6.dist-info/WHEEL
opam-1.0.6.dist-info/top_level.txt
opam-1.0.6.dist-info/RECORD
